{
    "birth_year": "896BBY",
    "created": "2014-12-15T12:26:01.042000Z",
    "edited": "2014-12-20T21:17:50.345000Z",
    "eye_color": "brown",
    "films": [
        "https://gotev.github.io/swapi-android/films/2/",
        "https://gotev.github.io/swapi-android/films/5/",
        "https://gotev.github.io/swapi-android/films/4/",
        "https://gotev.github.io/swapi-android/films/6/",
        "https://gotev.github.io/swapi-android/films/3/"
    ],
    "gender": "male",
    "hair_color": "white",
    "height": "66",
    "homeworld": "https://gotev.github.io/swapi-android/planets/28/",
    "mass": "17",
    "name": "Yoda",
    "skin_color": "green",
    "species": [
        "https://gotev.github.io/swapi-android/species/6/"
    ],
    "starships": [],
    "url": "https://gotev.github.io/swapi-android/people/20/",
    "vehicles": []
}
