{
    "cargo_capacity": "50000",
    "consumables": "2 months",
    "cost_in_credits": "150000",
    "created": "2014-12-10T15:36:25.724000Z",
    "crew": "46",
    "edited": "2014-12-22T18:21:15.523587Z",
    "films": [
        "https://gotev.github.io/swapi-android/films/5/",
        "https://gotev.github.io/swapi-android/films/1/"
    ],
    "length": "36.8",
    "manufacturer": "Corellia Mining Corporation",
    "max_atmosphering_speed": "30",
    "model": "Digger Crawler",
    "name": "Sand Crawler",
    "passengers": "30",
    "pilots": [],
    "url": "https://gotev.github.io/swapi-android/vehicles/4/",
    "vehicle_class": "wheeled"
}
